mcp_seniverse_weather_chenzp/__init__.py
mcp_seniverse_weather_chenzp/__main__.py
mcp_seniverse_weather_chenzp/server.py
mcp_seniverse_weather_chenzp-1.0.1.dist-info/METADATA
mcp_seniverse_weather_chenzp-1.0.1.dist-info/WHEEL
mcp_seniverse_weather_chenzp-1.0.1.dist-info/entry_points.txt
mcp_seniverse_weather_chenzp-1.0.1.dist-info/RECORD
