Metadata-Version: 2.4
Name: mcp-seniverse-weather-chenzp
Version: 1.0.1
Summary: Weather Forecast MCP Server Fowered by Seniverse
Requires-Python: >=3.10
Requires-Dist: mcp[cli]>=1.6.0
Requires-Dist: requests>=2.32.5
